kuantsol_transformation/__init__.py
kuantsol_transformation/financial.py
kuantsol_transformation/mathematical.py
kuantsol_transformation/normalization.py
kuantsol_transformation/time_dependent.py
kuantsol_transformation/two_data.py
kuantsol_transformation-0.0.5.dist-info/METADATA
kuantsol_transformation-0.0.5.dist-info/WHEEL
kuantsol_transformation-0.0.5.dist-info/top_level.txt
kuantsol_transformation-0.0.5.dist-info/RECORD
