Metadata-Version: 2.1
Name: kuantsol-transformation
Version: 0.0.5
Summary: Kuantsol Transformation Package
Author: Barış Coşkun
Author-email: <baris.coskun@kuantsol.ai>
Keywords: python,kuantsol_transformation
Classifier: Programming Language :: Python :: 3
Requires-Dist: numpy ==1.25.2
Requires-Dist: pandas ==1.5.2
Requires-Dist: scikit-learn <1.3.2
Requires-Dist: statsmodels ==0.13.5
